README.md
setup.py
jiange/__init__.py
jiange/agentbase.py
jiange/file.py
jiange/log.py
jiange/misc.py
jiange/time.py
jiange.egg-info/PKG-INFO
jiange.egg-info/SOURCES.txt
jiange.egg-info/dependency_links.txt
jiange.egg-info/not-zip-safe
jiange.egg-info/requires.txt
jiange.egg-info/top_level.txt
test/test_func.py