Metadata-Version: 1.0
Name: jiange
Version: 0.2.2
Summary: functions to save your life
Home-page: http://github.com/linjianz
Author: Zhang Linjian
Author-email: zhanglinjian1@gmail.com
License: MIT
Platform: UNKNOWN
